scripts/__init__.py
scripts/html_utils.py
scripts/html_writing.py
scripts/main.py
scripts/processing_files.py
scripts/similarity.py
scripts/template.html
scripts/utils.py
tests/__init__.py
tests/scripts/__init__.py
tests/scripts/test_html_utils.py
tests/scripts/test_html_writing.py
tests/scripts/test_main.py
tests/scripts/test_processing_files.py
tests/scripts/test_similarity.py
tests/scripts/test_utils.py
copy_spotter-0.1.16.dist-info/LICENSE
copy_spotter-0.1.16.dist-info/METADATA
copy_spotter-0.1.16.dist-info/WHEEL
copy_spotter-0.1.16.dist-info/entry_points.txt
copy_spotter-0.1.16.dist-info/top_level.txt
copy_spotter-0.1.16.dist-info/RECORD
